{ 
 "collision0":{
         "id":"0",
         "name":"",
         "life":"",
         "icon":"",
         "type":"",
         "visible":false,
         "locX":0,
         "locY":0,
         "status":"COLLISION_ACTIVITY",
        "velocity":5

    },
 "collision1":{
         "id":"1",
         "name":"land",
         "life":"",
         "icon":"object_002.png",
         "type":"COLLISION_GROUND",
         "visible":false,
         "locX":0,
         "locY":0,
         "status":"COLLISION_ACTIVITY",
        "velocity":5
    },
 "collision7":{
        "id":"7",
        "name":"land2",
        "life":"",
        "icon":"object_003.png",
        "type":"COLLISION_GROUND",
        "visible":false,
        "locX":0,
        "locY":0,
        "status":"COLLISION_ACTIVITY",
        "velocity":5
    },
 "collision57":{
        "id":"57",
        "name":"jian",
        "life":"",
        "icon":"object_004.png",
        "type":"COLLISION_NOWAY",
        "visible":false,
        "locX":0,
        "locY":0,
        "status":"COLLISION_ACTIVITY",
        "velocity":5
    },
 "collision60":{
        "id":"60",
        "name":"Shibei",
        "life":"",
        "icon":"object_001.png",
        "type":"COLLISION_NOWAY",
        "visible":false,
        "locX":0,
        "locY":0,
        "status":"COLLISION_ACTIVITY",
        "velocity":5
    },
 "collision62":{
        "id":"62",
        "name":"Dici2",
        "life":"",
        "icon":"object_006.png",
        "type":"COLLISION_SNARE",
        "visible":false,
        "locX":0,
        "locY":0,
        "status":"COLLISION_ACTIVITY",
        "velocity":5
    },
    "collision90":{
        "id":"90",
        "name":"Dici",
        "life":"",
        "icon":"object_005.png",
        "type":"COLLISION_SNARE",
        "visible":false,
        "locX":0,
        "locY":0,
        "status":"COLLISION_ACTIVITY",
        "velocity":5
    }

}